ai_ghostfunctions/__init__.py
ai_ghostfunctions/ghostfunctions.py
ai_ghostfunctions/keywords.py
ai_ghostfunctions/py.typed
ai_ghostfunctions/types.py
ai_ghostfunctions-0.6.1.dist-info/LICENSE
ai_ghostfunctions-0.6.1.dist-info/METADATA
ai_ghostfunctions-0.6.1.dist-info/WHEEL
ai_ghostfunctions-0.6.1.dist-info/RECORD
