Metadata-Version: 2.1
Name: ai-ghostfunctions
Version: 0.6.1
Summary: AI Ghostfunctions
Home-page: https://github.com/bmritz/ai-ghostfunctions
License: MIT
Author: Brian M. Ritz
Author-email: brianmritz@gmail.com
Requires-Python: >=3.8,<4.0
Classifier: Development Status :: 3 - Alpha
Classifier: License :: OSI Approved :: MIT License
Classifier: Programming Language :: Python :: 3
Classifier: Programming Language :: Python :: 3.8
Classifier: Programming Language :: Python :: 3.9
Classifier: Programming Language :: Python :: 3.10
Classifier: Programming Language :: Python :: 3.11
Requires-Dist: openai (>=1,<2)
Requires-Dist: typeguard (>=3,<5)
Project-URL: Changelog, https://github.com/bmritz/ai-ghostfunctions/releases
Project-URL: Documentation, https://ai-ghostfunctions.readthedocs.io
Project-URL: Repository, https://github.com/bmritz/ai-ghostfunctions
